DESCRIPTION.rst
MANIFEST.in
README.rst
setup.cfg
setup.py
paramikope/__init__.py
paramikope/paramikope.py
paramikope.egg-info/PKG-INFO
paramikope.egg-info/SOURCES.txt
paramikope.egg-info/dependency_links.txt
paramikope.egg-info/requires.txt
paramikope.egg-info/top_level.txt