Metadata-Version: 1.0
Name: paramikope
Version: 1.0.0
Summary: A sample Python project
Home-page: https://github.com/abyeipe88/paramiko-pexpect
Author: Aby Alex
Author-email: abyeipe88@gmail.com
License: MIT
Keywords: sample paramiko-pexpect
Platform: UNKNOWN
